microgpt/__init__.py
microgpt/input.txt
microgpt/meta.pkl
microgpt/model.py
microgpt/prepare_dataset.py
microgpt/sample.py
microgpt/pretrain/__init__.py
microgpt/pretrain/clm_pretrain_v0.py
microgpt/pretrain/config.py
microgpt/pretrain/configurator.py
microgpt-0.0.2.dist-info/licenses/LICENSE
microgpt-0.0.2.dist-info/METADATA
microgpt-0.0.2.dist-info/WHEEL
microgpt-0.0.2.dist-info/top_level.txt
microgpt-0.0.2.dist-info/RECORD
