Metadata-Version: 2.4
Name: microgpt
Version: 0.0.2
Summary: Lightweight GPT implementation designed for resource-constrained environments
Home-page: https://github.com/henrywoo/microgpt
Author: Wu Fuheng
Author-email: wufuheng@gmail.com
License: Apache 2
Project-URL: Bug Tracker, https://github.com/henrywoo/microgpt/issues
Project-URL: Documentation, https://github.com/henrywoo/microgpt#readme
Project-URL: Source Code, https://github.com/henrywoo/microgpt
Keywords: gpt,transformer,language-model,nlp,machine-learning,deep-learning,pytorch,lightweight,micro,resource-efficient
Platform: any
Classifier: Development Status :: 3 - Alpha
Classifier: Intended Audience :: Developers
Classifier: Intended Audience :: Science/Research
Classifier: License :: OSI Approved :: Apache Software License
Classifier: Operating System :: OS Independent
Classifier: Programming Language :: Python :: 3
Classifier: Programming Language :: Python :: 3.8
Classifier: Programming Language :: Python :: 3.9
Classifier: Programming Language :: Python :: 3.10
Classifier: Programming Language :: Python :: 3.11
Classifier: Topic :: Scientific/Engineering :: Artificial Intelligence
Classifier: Topic :: Software Development :: Libraries :: Python Modules
Classifier: Topic :: Text Processing :: Linguistic
Requires-Python: >=3.8
License-File: LICENSE
Requires-Dist: setuptools>=65.0.0
Requires-Dist: torch>=2.0.0
Requires-Dist: numpy>=1.21.0
Requires-Dist: tqdm>=4.64.0
Requires-Dist: hiq-python
Dynamic: author
Dynamic: author-email
Dynamic: classifier
Dynamic: description
Dynamic: description-content-type
Dynamic: home-page
Dynamic: keywords
Dynamic: license
Dynamic: license-file
Dynamic: platform
Dynamic: project-url
Dynamic: requires-dist
Dynamic: requires-python
Dynamic: summary
